eth_abi_lite/__init__.py
eth_abi_lite/abi.py
eth_abi_lite/base.py
eth_abi_lite/codec.py
eth_abi_lite/constants.py
eth_abi_lite/decoding.py
eth_abi_lite/encoding.py
eth_abi_lite/exceptions.py
eth_abi_lite/grammar.py
eth_abi_lite/packed.py
eth_abi_lite/py.typed
eth_abi_lite/registry.py
eth_abi_lite/tools/__init__.py
eth_abi_lite/tools/_strategies.py
eth_abi_lite/utils/__init__.py
eth_abi_lite/utils/numeric.py
eth_abi_lite/utils/padding.py
eth_abi_lite/utils/string.py
eth_typing_lite/__init__.py
eth_utils_lite/__init__.py
eth_utils_lite/abi.py
eth_utils_lite/address.py
eth_utils_lite/conversions.py
eth_utils_lite/crypto.py
eth_utils_lite/decorators.py
eth_utils_lite/encoding.py
eth_utils_lite/functional.py
eth_utils_lite/hexadecimal.py
eth_utils_lite/types.py
parsimonious_lite/__init__.py
parsimonious_lite/exceptions.py
parsimonious_lite/expressions.py
parsimonious_lite/grammar.py
parsimonious_lite/nodes.py
parsimonious_lite/utils.py
six_lite/__init__.py
six_lite/six_lite.py
eth_abi_lite-3.2.0.dist-info/LICENSE
eth_abi_lite-3.2.0.dist-info/METADATA
eth_abi_lite-3.2.0.dist-info/WHEEL
eth_abi_lite-3.2.0.dist-info/top_level.txt
eth_abi_lite-3.2.0.dist-info/RECORD
