Metadata-Version: 2.1
Name: eth-abi-lite
Version: 3.2.0
Summary: eth_abi_lite is a lite fork of `eth_abi`, aiming to support EVM abi encode/decode functionality without external dependencies on `eth_utils`, `eth_typing`, `toolz`, or `cytoolz`
Home-page: https://github.com/sslivkoff/eth-abi-lite
License: MIT
Keywords: ethereum
Classifier: Development Status :: 5 - Production/Stable
Classifier: Intended Audience :: Developers
Classifier: License :: OSI Approved :: MIT License
Classifier: Natural Language :: English
Classifier: Programming Language :: Python :: 3
Classifier: Programming Language :: Python :: 3.7
Classifier: Programming Language :: Python :: 3.8
Classifier: Programming Language :: Python :: 3.9
Classifier: Programming Language :: Python :: 3.10
Requires-Python: >=3.7, <4
License-File: LICENSE
Provides-Extra: dev
Requires-Dist: bumpversion (<1,>=0.5.3) ; extra == 'dev'
Requires-Dist: pytest-watch (<5,>=4.1.0) ; extra == 'dev'
Requires-Dist: wheel ; extra == 'dev'
Requires-Dist: twine ; extra == 'dev'
Requires-Dist: ipython ; extra == 'dev'
Requires-Dist: pytest (<7,>=6.2.5) ; extra == 'dev'
Requires-Dist: pytest-pythonpath (>=0.7.1) ; extra == 'dev'
Requires-Dist: pytest-xdist (<3,>=2.5.0) ; extra == 'dev'
Requires-Dist: tox (<3,>=2.9.1) ; extra == 'dev'
Requires-Dist: eth-hash[pycryptodome] ; extra == 'dev'
Requires-Dist: toolz ; extra == 'dev'
Requires-Dist: hypothesis (<5.0.0,>=4.18.2) ; extra == 'dev'
Requires-Dist: flake8 (==4.0.1) ; extra == 'dev'
Requires-Dist: isort (<5,>=4.2.15) ; extra == 'dev'
Requires-Dist: mypy (==0.910) ; extra == 'dev'
Requires-Dist: pydocstyle (<4,>=3.0.0) ; extra == 'dev'
Requires-Dist: Sphinx (<2,>=1.6.5) ; extra == 'dev'
Requires-Dist: sphinx-rtd-theme (>=0.1.9) ; extra == 'dev'
Requires-Dist: towncrier (<20,>=19.2.0) ; extra == 'dev'
Provides-Extra: doc
Requires-Dist: Sphinx (<2,>=1.6.5) ; extra == 'doc'
Requires-Dist: sphinx-rtd-theme (>=0.1.9) ; extra == 'doc'
Requires-Dist: towncrier (<20,>=19.2.0) ; extra == 'doc'
Provides-Extra: lint
Requires-Dist: flake8 (==4.0.1) ; extra == 'lint'
Requires-Dist: isort (<5,>=4.2.15) ; extra == 'lint'
Requires-Dist: mypy (==0.910) ; extra == 'lint'
Requires-Dist: pydocstyle (<4,>=3.0.0) ; extra == 'lint'
Provides-Extra: test
Requires-Dist: pytest (<7,>=6.2.5) ; extra == 'test'
Requires-Dist: pytest-pythonpath (>=0.7.1) ; extra == 'test'
Requires-Dist: pytest-xdist (<3,>=2.5.0) ; extra == 'test'
Requires-Dist: tox (<3,>=2.9.1) ; extra == 'test'
Requires-Dist: eth-hash[pycryptodome] ; extra == 'test'
Requires-Dist: toolz ; extra == 'test'
Requires-Dist: hypothesis (<5.0.0,>=4.18.2) ; extra == 'test'
Provides-Extra: tools
Requires-Dist: hypothesis (<5.0.0,>=4.18.2) ; extra == 'tools'
